straditize/__init__.py
straditize/__main__.py
straditize/binary.py
straditize/colnames.py
straditize/common.py
straditize/cross_mark.py
straditize/evaluator.py
straditize/label_selection.py
straditize/magnifier.py
straditize/straditizer.py
straditize/version.py
straditize/widgets/__init__.py
straditize/widgets/axes_translations.py
straditize/widgets/colnames.py
straditize/widgets/data.py
straditize/widgets/image_correction.py
straditize/widgets/marker_control.py
straditize/widgets/menu_actions.py
straditize/widgets/pattern_selection.py
straditize/widgets/plots.py
straditize/widgets/progress_widget.py
straditize/widgets/samples_table.py
straditize/widgets/selection_toolbar.py
straditize/widgets/stacked_area_reader.py
straditize/widgets/docs/align_column1-2.png
straditize/widgets/docs/align_column1.png
straditize/widgets/docs/align_column2-2.png
straditize/widgets/docs/align_column2.png
straditize/widgets/docs/align_columns.rst
straditize/widgets/docs/area-diagram.png
straditize/widgets/docs/axes_translations.rst
straditize/widgets/docs/bar-diagram-digitization.png
straditize/widgets/docs/bar-diagram-splitting.png
straditize/widgets/docs/bar-diagram-splitting2.png
straditize/widgets/docs/bar-diagram.png
straditize/widgets/docs/basic_diagram_cross_col.png
straditize/widgets/docs/basic_diagram_disconnected.png
straditize/widgets/docs/basic_diagram_disconnected_01.png
straditize/widgets/docs/basic_diagram_disconnected_02.png
straditize/widgets/docs/basic_diagram_disconnected_03.png
straditize/widgets/docs/basic_diagram_exaggerated.png
straditize/widgets/docs/basic_diagram_features_at_col_ends.png
straditize/widgets/docs/basic_diagram_hlines.png
straditize/widgets/docs/basic_diagram_small_features.png
straditize/widgets/docs/basic_diagram_vlines.png
straditize/widgets/docs/basic_diagram_xaxes.png
straditize/widgets/docs/basic_diagram_yaxes.png
straditize/widgets/docs/child-readers.png
straditize/widgets/docs/child_readers.rst
straditize-0.1.3.post1.dist-info/LICENSE
straditize-0.1.3.post1.dist-info/METADATA
straditize-0.1.3.post1.dist-info/WHEEL
straditize-0.1.3.post1.dist-info/entry_points.txt
straditize-0.1.3.post1.dist-info/top_level.txt
straditize-0.1.3.post1.dist-info/RECORD
