Metadata-Version: 2.1
Name: straditize
Version: 0.1.3.post1
Summary: Python package for digitizing pollen diagrams
Home-page: https://github.com/Chilipp/straditize
Author: Philipp Sommer
Author-email: philipp.sommer@unil.ch
License: GPLv3
Keywords: visualization earth-sciences paleo climate paleoclimate pollen diagram digitization database
Classifier: Development Status :: 7 - Inactive
Classifier: Intended Audience :: Science/Research
Classifier: Topic :: Scientific/Engineering :: Visualization
Classifier: Topic :: Scientific/Engineering :: GIS
Classifier: Topic :: Scientific/Engineering
Classifier: License :: OSI Approved :: GNU General Public License v3 (GPLv3)
Classifier: Programming Language :: Python :: 3
Classifier: Programming Language :: Python :: 3.6
Classifier: Programming Language :: Python :: 3.7
Classifier: Operating System :: OS Independent
License-File: LICENSE
Requires-Dist: psyplot-gui >=1.2.3
Requires-Dist: psyplot >=1.2.0
Requires-Dist: psy-strat
Requires-Dist: scipy
Requires-Dist: scikit-image
Requires-Dist: openpyxl
Requires-Dist: netCDF4
Requires-Dist: pyqt5 !=5.12
Requires-Dist: PyQtWebEngine
Requires-Dist: pyqt5-sip
